
[
  {
    "CommitCharge": 512,
    "Disasm": "\"\n0x1526f890000:\tand\tbyte ptr [rax], al\n0x1526f890002:\tadd\tbyte ptr [rax], al\n0x1526f890004:\tloopne\t0x1526f890005\"",
    "End VPN": 1453572292607,
    "File output": "Disabled",
    "Hexdump": "20 00 00 00 e0 ff 1f 00 0c 00 00 00 01 00 07 00 00 42 00 30 00 70 00 60 00 50 00 c0 00 d0 00 00 09 00 38 00 09 00 01 05 ba fc ff ff ff 03 55 18 03 55 54 89 d7 b9 04 00 1a 00 ff 56 28 8b 4d 1c",
    "Notes": null,
    "PID": 2016,
    "PrivateMemory": 1,
    "Process": "MsMpEng.exe",
    "Protection": "PAGE_EXECUTE_READWRITE",
    "Start VPN": 1453570195456,
    "Tag": "VadS",
    "__children": []
  },
  {
    "CommitCharge": 256,
    "Disasm": "\"\n0x1526f790000:\tand\tbyte ptr [rax], al\n0x1526f790002:\tadd\tbyte ptr [rax], al\n0x1526f790004:\tloopne\t0x1526f790005\n0x1526f790006:\tstr\tword ptr [rax + rax]\n0x1526f79000a:\tadd\tbyte ptr [rax], al\n0x1526f79000c:\tadd\tdword ptr [rax], eax\"",
    "End VPN": 1453570195455,
    "File output": "Disabled",
    "Hexdump": "20 00 00 00 e0 ff 0f 00 0c 00 00 00 01 00 07 00 00 42 00 30 00 70 00 60 00 50 00 c0 00 d0 00 00 08 00 42 00 00 00 00 05 48 8b 45 20 48 89 c2 48 8b 45 18 48 8b 00 48 89 02 48 8b 45 20 81 00 b8",
    "Notes": null,
    "PID": 2016,
    "PrivateMemory": 1,
    "Process": "MsMpEng.exe",
    "Protection": "PAGE_EXECUTE_READWRITE",
    "Start VPN": 1453569146880,
    "Tag": "VadS",
    "__children": []
  },
  {
    "CommitCharge": 269,
    "Disasm": "\"\n0x1526fa90000:\tpush\trsi\n0x1526fa90001:\tpush\trdi\n0x1526fa90002:\tpush\trbx\n0x1526fa90003:\tpush\trbp\n0x1526fa90004:\tpush\tr12\n0x1526fa90006:\tpush\tr13\n0x1526fa90008:\tsub\trsp, 0x28\n0x1526fa9000c:\tmov\trbp, rcx\n0x1526fa9000f:\tlea\trsi, [rcx + 0x3888]\n0x1526fa90016:\tjmp\trdx\n0x1526fa90018:\tadd\trsp, 0x28\n0x1526fa9001c:\tpop\tr13\n0x1526fa9001e:\tpop\tr12\n0x1526fa90020:\tpop\trbp\n0x1526fa90021:\tpop\trbx\n0x1526fa90022:\tpop\trdi\n0x1526fa90023:\tpop\trsi\n0x1526fa90024:\tret\t\n0x1526fa90025:\tadd\tbyte ptr [rax], al\n0x1526fa90027:\tadd\tbyte ptr [rax], al\n0x1526fa90029:\tadd\tbyte ptr [rax], al\n0x1526fa9002b:\tadd\tbyte ptr [rax], al\n0x1526fa9002d:\tadd\tbyte ptr [rax], al\n0x1526fa9002f:\tadd\tbyte ptr [rax], al\n0x1526fa90031:\tadd\tbyte ptr [rax], al\n0x1526fa90033:\tadd\tbyte ptr [rax], al\n0x1526fa90035:\tadd\tbyte ptr [rax], al\n0x1526fa90037:\tadd\tbyte ptr [rax], al\n0x1526fa90039:\tadd\tbyte ptr [rax], al\n0x1526fa9003b:\tadd\tbyte ptr [rax], al\n0x1526fa9003d:\tadd\tbyte ptr [rax], al\"",
    "End VPN": 1453573394431,
    "File output": "Disabled",
    "Hexdump": "56 57 53 55 41 54 41 55 48 83 ec 28 48 8b e9 48 8d b1 88 38 00 00 ff e2 48 83 c4 28 41 5d 41 5c 5d 5b 5f 5e c3 00 00 00 00 00 00 00 00 00 00 00 00 00 00 00 00 00 00 00 00 00 00 00 00 00 00 00",
    "Notes": null,
    "PID": 2016,
    "PrivateMemory": 1,
    "Process": "MsMpEng.exe",
    "Protection": "PAGE_EXECUTE_READWRITE",
    "Start VPN": 1453572292608,
    "Tag": "VadS",
    "__children": []
  },
  {
    "CommitCharge": 269,
    "Disasm": "\"\n0x1526fd70000:\tpush\trsi\n0x1526fd70001:\tpush\trdi\n0x1526fd70002:\tpush\trbx\n0x1526fd70003:\tpush\trbp\n0x1526fd70004:\tpush\tr12\n0x1526fd70006:\tpush\tr13\n0x1526fd70008:\tsub\trsp, 0x28\n0x1526fd7000c:\tmov\trbp, rcx\n0x1526fd7000f:\tlea\trsi, [rcx + 0x3888]\n0x1526fd70016:\tjmp\trdx\n0x1526fd70018:\tadd\trsp, 0x28\n0x1526fd7001c:\tpop\tr13\n0x1526fd7001e:\tpop\tr12\n0x1526fd70020:\tpop\trbp\n0x1526fd70021:\tpop\trbx\n0x1526fd70022:\tpop\trdi\n0x1526fd70023:\tpop\trsi\n0x1526fd70024:\tret\t\n0x1526fd70025:\tadd\tbyte ptr [rax], al\n0x1526fd70027:\tadd\tbyte ptr [rax], al\n0x1526fd70029:\tadd\tbyte ptr [rax], al\n0x1526fd7002b:\tadd\tbyte ptr [rax], al\n0x1526fd7002d:\tadd\tbyte ptr [rax], al\n0x1526fd7002f:\tadd\tbyte ptr [rax], al\n0x1526fd70031:\tadd\tbyte ptr [rax], al\n0x1526fd70033:\tadd\tbyte ptr [rax], al\n0x1526fd70035:\tadd\tbyte ptr [rax], al\n0x1526fd70037:\tadd\tbyte ptr [rax], al\n0x1526fd70039:\tadd\tbyte ptr [rax], al\n0x1526fd7003b:\tadd\tbyte ptr [rax], al\n0x1526fd7003d:\tadd\tbyte ptr [rax], al\"",
    "End VPN": 1453576409087,
    "File output": "Disabled",
    "Hexdump": "56 57 53 55 41 54 41 55 48 83 ec 28 48 8b e9 48 8d b1 88 38 00 00 ff e2 48 83 c4 28 41 5d 41 5c 5d 5b 5f 5e c3 00 00 00 00 00 00 00 00 00 00 00 00 00 00 00 00 00 00 00 00 00 00 00 00 00 00 00",
    "Notes": null,
    "PID": 2016,
    "PrivateMemory": 1,
    "Process": "MsMpEng.exe",
    "Protection": "PAGE_EXECUTE_READWRITE",
    "Start VPN": 1453575307264,
    "Tag": "VadS",
    "__children": []
  },
  {
    "CommitCharge": 269,
    "Disasm": "\"\n0x15270050000:\tpush\trsi\n0x15270050001:\tpush\trdi\n0x15270050002:\tpush\trbx\n0x15270050003:\tpush\trbp\n0x15270050004:\tpush\tr12\n0x15270050006:\tpush\tr13\n0x15270050008:\tsub\trsp, 0x28\n0x1527005000c:\tmov\trbp, rcx\n0x1527005000f:\tlea\trsi, [rcx + 0x3888]\n0x15270050016:\tjmp\trdx\n0x15270050018:\tadd\trsp, 0x28\n0x1527005001c:\tpop\tr13\n0x1527005001e:\tpop\tr12\n0x15270050020:\tpop\trbp\n0x15270050021:\tpop\trbx\n0x15270050022:\tpop\trdi\n0x15270050023:\tpop\trsi\n0x15270050024:\tret\t\n0x15270050025:\tadd\tbyte ptr [rax], al\n0x15270050027:\tadd\tbyte ptr [rax], al\n0x15270050029:\tadd\tbyte ptr [rax], al\n0x1527005002b:\tadd\tbyte ptr [rax], al\n0x1527005002d:\tadd\tbyte ptr [rax], al\n0x1527005002f:\tadd\tbyte ptr [rax], al\n0x15270050031:\tadd\tbyte ptr [rax], al\n0x15270050033:\tadd\tbyte ptr [rax], al\n0x15270050035:\tadd\tbyte ptr [rax], al\n0x15270050037:\tadd\tbyte ptr [rax], al\n0x15270050039:\tadd\tbyte ptr [rax], al\n0x1527005003b:\tadd\tbyte ptr [rax], al\n0x1527005003d:\tadd\tbyte ptr [rax], al\"",
    "End VPN": 1453579423743,
    "File output": "Disabled",
    "Hexdump": "56 57 53 55 41 54 41 55 48 83 ec 28 48 8b e9 48 8d b1 88 38 00 00 ff e2 48 83 c4 28 41 5d 41 5c 5d 5b 5f 5e c3 00 00 00 00 00 00 00 00 00 00 00 00 00 00 00 00 00 00 00 00 00 00 00 00 00 00 00",
    "Notes": null,
    "PID": 2016,
    "PrivateMemory": 1,
    "Process": "MsMpEng.exe",
    "Protection": "PAGE_EXECUTE_READWRITE",
    "Start VPN": 1453578321920,
    "Tag": "VadS",
    "__children": []
  },
  {
    "CommitCharge": 16,
    "Disasm": "\"\n0x20008030000:\tadd\tbyte ptr [rax], al\n0x20008030002:\tadd\tbyte ptr [rax], al\n0x20008030004:\tadd\tbyte ptr [rax], al\n0x20008030006:\tadd\tbyte ptr [rax], al\n0x20008030008:\tadd\tbyte ptr [rax], al\n0x2000803000a:\tadd\tbyte ptr [rax], al\n0x2000803000c:\tadd\tbyte ptr [rax], al\n0x2000803000e:\tadd\tbyte ptr [rax], al\n0x20008030010:\tadd\tbyte ptr [rax], al\n0x20008030012:\tadd\tbyte ptr [rax], al\n0x20008030014:\tadd\tbyte ptr [rax], al\n0x20008030016:\tadd\tbyte ptr [rax], al\n0x20008030018:\tadd\tbyte ptr [rax], al\n0x2000803001a:\tadd\tbyte ptr [rax], al\n0x2000803001c:\tadd\tbyte ptr [rax], al\n0x2000803001e:\tadd\tbyte ptr [rax], al\n0x20008030020:\tadd\tbyte ptr [rax], al\n0x20008030022:\tadd\tbyte ptr [rax], al\n0x20008030024:\tadd\tbyte ptr [rax], al\n0x20008030026:\tadd\tbyte ptr [rax], al\n0x20008030028:\tadd\tbyte ptr [rax], al\n0x2000803002a:\tadd\tbyte ptr [rax], al\n0x2000803002c:\tadd\tbyte ptr [rax], al\n0x2000803002e:\tadd\tbyte ptr [rax], al\n0x20008030030:\tadd\tbyte ptr [rax], al\n0x20008030032:\tadd\tbyte ptr [rax], al\n0x20008030034:\tadd\tbyte ptr [rax], al\n0x20008030036:\tadd\tbyte ptr [rax], al\n0x20008030038:\tadd\tbyte ptr [rax], al\n0x2000803003a:\tadd\tbyte ptr [rax], al\n0x2000803003c:\tadd\tbyte ptr [rax], al\n0x2000803003e:\tadd\tbyte ptr [rax], al\"",
    "End VPN": 2199157735423,
    "File output": "Disabled",
    "Hexdump": "00 00 00 00 00 00 00 00 00 00 00 00 00 00 00 00 00 00 00 00 00 00 00 00 00 00 00 00 00 00 00 00 00 00 00 00 00 00 00 00 00 00 00 00 00 00 00 00 00 00 00 00 00 00 00 00 00 00 00 00 00 00 00 00",
    "Notes": null,
    "PID": 880,
    "PrivateMemory": 1,
    "Process": "RuntimeBroker.",
    "Protection": "PAGE_EXECUTE_READ",
    "Start VPN": 2199157669888,
    "Tag": "VadS",
    "__children": []
  },
  {
    "CommitCharge": 1,
    "Disasm": "\"\n0x2483c900000:\tmov\tqword ptr [rsp + 0x10], rdx\n0x2483c900005:\tmov\tqword ptr [rsp + 8], rcx\n0x2483c90000a:\tmov\tqword ptr [rsp + 0x18], r8\n0x2483c90000f:\tmov\tqword ptr [rsp + 0x20], r9\n0x2483c900014:\tmov\trax, qword ptr [rcx + 0x28]\n0x2483c900018:\tmov\trcx, qword ptr [rax + 8]\n0x2483c90001c:\tmov\trdx, qword ptr [rcx + 0x50]\n0x2483c900020:\tand\trdx, 0xfffffffffffffff8\n0x2483c900024:\tmov\trcx, rdx\n0x2483c900027:\tmovabs\trax, 0x2483c900060\n0x2483c900031:\tsub\trcx, rax\n0x2483c900034:\tcmp\trcx, 0xf70\n0x2483c90003b:\tjbe\t0x2483c900046\"",
    "End VPN": 2509277102079,
    "File output": "Disabled",
    "Hexdump": "48 89 54 24 10 48 89 4c 24 08 4c 89 44 24 18 4c 89 4c 24 20 48 8b 41 28 48 8b 48 08 48 8b 51 50 48 83 e2 f8 48 8b ca 48 b8 60 00 90 3c 48 02 00 00 48 2b c8 48 81 f9 70 0f 00 00 76 09 48 c7 c1",
    "Notes": null,
    "PID": 5380,
    "PrivateMemory": 1,
    "Process": "smartscreen.ex",
    "Protection": "PAGE_EXECUTE_READWRITE",
    "Start VPN": 2509276971008,
    "Tag": "VadS",
    "__children": []
  },
  {
    "CommitCharge": 1,
    "Disasm": "\"\n0x2483d210000:\tmov\tqword ptr [rsp + 0x10], rdx\n0x2483d210005:\tmov\tqword ptr [rsp + 8], rcx\n0x2483d21000a:\tmov\tqword ptr [rsp + 0x18], r8\n0x2483d21000f:\tmov\tqword ptr [rsp + 0x20], r9\n0x2483d210014:\tmov\trax, qword ptr [rcx + 0x28]\n0x2483d210018:\tmov\trcx, qword ptr [rax + 8]\n0x2483d21001c:\tmov\trdx, qword ptr [rcx + 0x50]\n0x2483d210020:\tand\trdx, 0xfffffffffffffff8\n0x2483d210024:\tmov\trcx, rdx\n0x2483d210027:\tmovabs\trax, 0x2483d210060\n0x2483d210031:\tsub\trcx, rax\n0x2483d210034:\tcmp\trcx, 0xf70\n0x2483d21003b:\tjbe\t0x2483d210046\"",
    "End VPN": 2509286604799,
    "File output": "Disabled",
    "Hexdump": "48 89 54 24 10 48 89 4c 24 08 4c 89 44 24 18 4c 89 4c 24 20 48 8b 41 28 48 8b 48 08 48 8b 51 50 48 83 e2 f8 48 8b ca 48 b8 60 00 21 3d 48 02 00 00 48 2b c8 48 81 f9 70 0f 00 00 76 09 48 c7 c1",
    "Notes": null,
    "PID": 5380,
    "PrivateMemory": 1,
    "Process": "smartscreen.ex",
    "Protection": "PAGE_EXECUTE_READWRITE",
    "Start VPN": 2509286473728,
    "Tag": "VadS",
    "__children": []
  },
  {
    "CommitCharge": 1,
    "Disasm": "\"\n0x2484d430000:\tmov\tqword ptr [rsp + 0x10], rdx\n0x2484d430005:\tmov\tqword ptr [rsp + 8], rcx\n0x2484d43000a:\tmov\tqword ptr [rsp + 0x18], r8\n0x2484d43000f:\tmov\tqword ptr [rsp + 0x20], r9\n0x2484d430014:\tmov\trax, qword ptr [rcx + 0x28]\n0x2484d430018:\tmov\trcx, qword ptr [rax + 8]\n0x2484d43001c:\tmov\trdx, qword ptr [rcx + 0x50]\n0x2484d430020:\tand\trdx, 0xfffffffffffffff8\n0x2484d430024:\tmov\trcx, rdx\n0x2484d430027:\tmovabs\trax, 0x2484d430060\n0x2484d430031:\tsub\trcx, rax\n0x2484d430034:\tcmp\trcx, 0xf70\n0x2484d43003b:\tjbe\t0x2484d430046\"",
    "End VPN": 2509557268479,
    "File output": "Disabled",
    "Hexdump": "48 89 54 24 10 48 89 4c 24 08 4c 89 44 24 18 4c 89 4c 24 20 48 8b 41 28 48 8b 48 08 48 8b 51 50 48 83 e2 f8 48 8b ca 48 b8 60 00 43 4d 48 02 00 00 48 2b c8 48 81 f9 70 0f 00 00 76 09 48 c7 c1",
    "Notes": null,
    "PID": 5380,
    "PrivateMemory": 1,
    "Process": "smartscreen.ex",
    "Protection": "PAGE_EXECUTE_READWRITE",
    "Start VPN": 2509557137408,
    "Tag": "VadS",
    "__children": []
  },
  {
    "CommitCharge": 1,
    "Disasm": "\"\n0x7df44f140000:\tadd\tbyte ptr [rax], al\n0x7df44f140002:\tadd\tbyte ptr [rax], al\n0x7df44f140004:\tadd\tbyte ptr [rax], al\n0x7df44f140006:\tadd\tbyte ptr [rax], al\n0x7df44f140008:\tjs\t0x7df44f140017\n0x7df44f14000a:\tadd\tbyte ptr [rax], al\n0x7df44f14000c:\tadd\tbyte ptr [rax], al\n0x7df44f14000e:\tadd\tbyte ptr [rax], al\n0x7df44f140010:\tor\tal, 0\n0x7df44f140012:\tadd\tbyte ptr [rax], al\n0x7df44f140014:\tmov\tr10, 0\n0x7df44f14001b:\tmovabs\trax, 0x7ffca9fe4a50\n0x7df44f140025:\tjmp\trax\n0x7df44f140027:\tmov\tr10, 1\n0x7df44f14002e:\tmovabs\trax, 0x7ffca9fe4a50\n0x7df44f140038:\tjmp\trax\"",
    "End VPN": 138488252268543,
    "File output": "Disabled",
    "Hexdump": "00 00 00 00 00 00 00 00 78 0d 00 00 00 00 00 00 0c 00 00 00 49 c7 c2 00 00 00 00 48 b8 50 4a fe a9 fc 7f 00 00 ff e0 49 c7 c2 01 00 00 00 48 b8 50 4a fe a9 fc 7f 00 00 ff e0 49 c7 c2 02 00 00",
    "Notes": null,
    "PID": 5736,
    "PrivateMemory": 1,
    "Process": "powershell.exe",
    "Protection": "PAGE_EXECUTE_READWRITE",
    "Start VPN": 138488252203008,
    "Tag": "VadS",
    "__children": []
  },
  {
    "CommitCharge": 2,
    "Disasm": "\"\n0x1624a9d0000:\tadd\tbyte ptr [rax], al\n0x1624a9d0002:\tadd\tbyte ptr [rax], al\n0x1624a9d0004:\tadd\tbyte ptr [rax], al\n0x1624a9d0006:\tadd\tbyte ptr [rax], al\n0x1624a9d0008:\tout\t0x7d, al\n0x1624a9d000a:\txor\tbyte ptr [rbx + rbx*4 - 0x11feffa9], ch\"",
    "End VPN": 1521670291455,
    "File output": "Disabled",
    "Hexdump": "00 00 00 00 00 00 00 00 e6 7d 30 ac 9b 57 00 01 ee ff ee ff 02 00 00 00 20 01 9d 4a 62 01 00 00 20 01 9d 4a 62 01 00 00 00 00 9d 4a 62 01 00 00 00 00 9d 4a 62 01 00 00 0f 00 00 00 00 00 00 00",
    "Notes": null,
    "PID": 5736,
    "PrivateMemory": 1,
    "Process": "powershell.exe",
    "Protection": "PAGE_EXECUTE_READWRITE",
    "Start VPN": 1521670225920,
    "Tag": "VadS",
    "__children": []
  },
  {
    "CommitCharge": 9,
    "Disasm": "\"\n0x16262c00000:\tadd\tbyte ptr [rax], al\n0x16262c00002:\tadd\tbyte ptr [rax], al\n0x16262c00004:\tadd\tbyte ptr [rax], al\n0x16262c00006:\tadd\tbyte ptr [rax], al\n0x16262c00008:\tfiadd\tdword ptr [rsi]\"",
    "End VPN": 1522075238399,
    "File output": "Disabled",
    "Hexdump": "00 00 00 00 00 00 00 00 da 06 d4 ba 35 4a 00 01 ee ff ee ff 02 00 00 00 20 01 c0 62 62 01 00 00 20 01 c0 62 62 01 00 00 00 00 c0 62 62 01 00 00 00 00 c0 62 62 01 00 00 0f 00 00 00 00 00 00 00",
    "Notes": null,
    "PID": 5736,
    "PrivateMemory": 1,
    "Process": "powershell.exe",
    "Protection": "PAGE_EXECUTE_READWRITE",
    "Start VPN": 1522075172864,
    "Tag": "VadS",
    "__children": []
  },
  {
    "CommitCharge": 1,
    "Disasm": "\"\n0x16262bf0000:\tadd\tbyte ptr [rax], al\n0x16262bf0002:\tadd\tbyte ptr [rax], al\n0x16262bf0004:\tadd\tbyte ptr [rax], al\n0x16262bf0006:\tadd\tbyte ptr [rax], al\n0x16262bf0008:\tcmp\tbyte ptr [rcx - 0x40], 0x62\"",
    "End VPN": 1522075135999,
    "File output": "Disabled",
    "Hexdump": "00 00 00 00 00 00 00 00 80 79 c0 62 62 01 00 00 80 79 c0 62 62 01 00 00 00 00 c0 62 62 01 00 00 b0 0d bf 62 62 01 00 00 00 10 bf 62 62 01 00 00 00 70 bf 62 62 01 00 00 01 00 00 00 00 00 00 00",
    "Notes": null,
    "PID": 5736,
    "PrivateMemory": 1,
    "Process": "powershell.exe",
    "Protection": "PAGE_EXECUTE_READWRITE",
    "Start VPN": 1522075107328,
    "Tag": "VadS",
    "__children": []
  },
  {
    "CommitCharge": 2,
    "Disasm": "\"\n0x7df44f150000:\tfdivr\tst(7)\"",
    "End VPN": 138488252923903,
    "File output": "Disabled",
    "Hexdump": "d8 ff ff ff ff ff ff ff 08 00 00 00 00 00 00 00 01 00 00 00 00 00 00 00 00 02 0e 03 38 00 00 00 68 01 d7 07 0c 00 00 00 d8 5d a0 a8 fc 7f 00 00 00 10 9e a8 fc 7f 00 00 08 4a b7 a8 fc 7f 00 00",
    "Notes": null,
    "PID": 5736,
    "PrivateMemory": 1,
    "Process": "powershell.exe",
    "Protection": "PAGE_EXECUTE_READWRITE",
    "Start VPN": 138488252268544,
    "Tag": "VadS",
    "__children": []
  }
]
